sms_sdk_renderer_python/__init__.py
sms_sdk_renderer_python/lib/__init__.py
sms_sdk_renderer_python/lib/helpers.py
sms_sdk_renderer_python/lib/sms_sdk_renderer.py
sms_sdk_renderer_python/templates/__init__.py
sms_sdk_renderer_python/templates/alert.hbs
sms_sdk_renderer_python/templates/button.hbs
sms_sdk_renderer_python/templates/checkbox.hbs
sms_sdk_renderer_python/templates/dropdown_menu.hbs
sms_sdk_renderer_python/templates/form.hbs
sms_sdk_renderer_python/templates/information.hbs
sms_sdk_renderer_python/templates/list.hbs
sms_sdk_renderer_python/templates/list_template.hbs
sms_sdk_renderer_python/templates/notification.hbs
sms_sdk_renderer_python/templates/personselector.hbs
sms_sdk_renderer_python/templates/radiobutton.hbs
sms_sdk_renderer_python/templates/simple.hbs
sms_sdk_renderer_python/templates/table.hbs
sms_sdk_renderer_python/templates/table_select.hbs
sms_sdk_renderer_python/templates/textarea.hbs
sms_sdk_renderer_python/templates/textfield.hbs
sms_sdk_renderer_python/test/__init__.py
sms_sdk_renderer_python/test/test.py
sms_sdk_renderer_python-0.1.8.dist-info/LICENSE
sms_sdk_renderer_python-0.1.8.dist-info/METADATA
sms_sdk_renderer_python-0.1.8.dist-info/WHEEL
sms_sdk_renderer_python-0.1.8.dist-info/top_level.txt
sms_sdk_renderer_python-0.1.8.dist-info/RECORD
