Metadata-Version: 2.1
Name: sms-sdk-renderer-python
Version: 0.1.8
Summary: Sample Renderer for Symphony Elements
Home-page: https://github.com/SymphonyPlatformSolutions/sms_sdk_renderer_python
Author: Reed Feldman
Author-email: reed.feldman@symphony.com
License: UNKNOWN
Platform: UNKNOWN
Classifier: Programming Language :: Python :: 3
Classifier: License :: OSI Approved :: MIT License
Classifier: Operating System :: OS Independent
Requires-Python: >=3.6
Requires-Dist: pybars3 (==0.9.6)
